opponent_adjusted_nba_scraper/__init__.py
opponent_adjusted_nba_scraper/data/bball-ref-teams.csv
opponent_adjusted_nba_scraper/data/nba-stats-teams.csv
opponent_adjusted_nba_scraper/data/player_names.csv
opponent_adjusted_nba_scraper/endpoints/__init__.py
opponent_adjusted_nba_scraper/endpoints/_base.py
opponent_adjusted_nba_scraper/endpoints/playerlogs.py
opponent_adjusted_nba_scraper/endpoints/playerstats.py
opponent_adjusted_nba_scraper/endpoints/teams.py
opponent_adjusted_nba_scraper/library/__init__.py
opponent_adjusted_nba_scraper/library/arguments.py
opponent_adjusted_nba_scraper/library/constants.py
opponent_adjusted_nba_scraper/library/parameters.py
opponent_adjusted_nba_scraper/library/request.py
opponent_adjusted_nba_scraper-1.0.24.dist-info/METADATA
opponent_adjusted_nba_scraper-1.0.24.dist-info/WHEEL
opponent_adjusted_nba_scraper-1.0.24.dist-info/licenses/LICENSE
opponent_adjusted_nba_scraper-1.0.24.dist-info/RECORD
