Metadata-Version: 2.4
Name: opponent_adjusted_nba_scraper
Version: 1.0.24
Dynamic: Requires-Dist
Dynamic: Keywords
Dynamic: License
Dynamic: License-Expression
Summary: A package for scraping data from basketball-reference.com and stats.nba.com to provide opponent-adjusted statistics. 
Author-email: Oscar Gutierrez Altamirano <oscargutierreza617@gmail.com>
License-File: LICENSE
Classifier: License :: OSI Approved :: MIT License
Classifier: Operating System :: OS Independent
Classifier: Programming Language :: Python :: 3
Requires-Python: >=3.7
